zotero_sync/__init__.py
zotero_sync/__main__.py
zotero_sync/api.py
zotero_sync-0.1.6.dist-info/entry_points.txt
zotero_sync-0.1.6.dist-info/WHEEL
zotero_sync-0.1.6.dist-info/METADATA
zotero_sync-0.1.6.dist-info/RECORD
